dictol/COPAR.py
dictol/DLSI.py
dictol/LRSDL.py
dictol/ODL.py
dictol/SRC.py
dictol/__init__.py
dictol/base.py
dictol/optimize.py
dictol/test_ODL.py
dictol/test_utils.py
dictol/utils.py
dictol-0.1.0.dist-info/LICENSE
dictol-0.1.0.dist-info/METADATA
dictol-0.1.0.dist-info/WHEEL
dictol-0.1.0.dist-info/top_level.txt
dictol-0.1.0.dist-info/RECORD
