Metadata-Version: 2.1
Name: dictol
Version: 0.1.0
Summary: A Toolbox for Discriminative Dictionary Learing
Home-page: https://github.com/tiepvupsu/dictol_python
Author: Tiep Vu
Author-email: vuhuutiep@gmail.com
License: UNKNOWN
Platform: UNKNOWN
Classifier: Programming Language :: Python :: 3
Classifier: License :: OSI Approved :: MIT License
Classifier: Operating System :: OS Independent
